odibi/__init__.py
odibi/__main__.py
odibi/catalog.py
odibi/catalog_sync.py
odibi/config.py
odibi/constants.py
odibi/context.py
odibi/derived_updater.py
odibi/enums.py
odibi/exceptions.py
odibi/graph.py
odibi/introspect.py
odibi/lineage.py
odibi/node.py
odibi/pipeline.py
odibi/plugins.py
odibi/project.py
odibi/references.py
odibi/registry.py
odibi/cli/__init__.py
odibi/cli/__main__.py
odibi/cli/catalog.py
odibi/cli/deploy.py
odibi/cli/doctor.py
odibi/cli/export.py
odibi/cli/graph.py
odibi/cli/init_pipeline.py
odibi/cli/lineage.py
odibi/cli/main.py
odibi/cli/run.py
odibi/cli/schema.py
odibi/cli/secrets.py
odibi/cli/story.py
odibi/cli/system.py
odibi/cli/test.py
odibi/cli/ui.py
odibi/cli/validate.py
odibi/connections/__init__.py
odibi/connections/azure_adls.py
odibi/connections/azure_sql.py
odibi/connections/base.py
odibi/connections/factory.py
odibi/connections/http.py
odibi/connections/local.py
odibi/connections/local_dbfs.py
odibi/diagnostics/__init__.py
odibi/diagnostics/delta.py
odibi/diagnostics/diff.py
odibi/diagnostics/manager.py
odibi/engine/__init__.py
odibi/engine/base.py
odibi/engine/pandas_engine.py
odibi/engine/polars_engine.py
odibi/engine/registry.py
odibi/engine/spark_engine.py
odibi/orchestration/__init__.py
odibi/orchestration/airflow.py
odibi/orchestration/dagster.py
odibi/patterns/__init__.py
odibi/patterns/aggregation.py
odibi/patterns/base.py
odibi/patterns/date_dimension.py
odibi/patterns/dimension.py
odibi/patterns/fact.py
odibi/patterns/merge.py
odibi/patterns/scd2.py
odibi/semantics/__init__.py
odibi/semantics/materialize.py
odibi/semantics/metrics.py
odibi/semantics/query.py
odibi/semantics/runner.py
odibi/semantics/story.py
odibi/semantics/views.py
odibi/state/__init__.py
odibi/story/__init__.py
odibi/story/doc_story.py
odibi/story/generator.py
odibi/story/lineage.py
odibi/story/lineage_utils.py
odibi/story/metadata.py
odibi/story/renderers.py
odibi/story/themes.py
odibi/story/templates/run_story.html
odibi/testing/__init__.py
odibi-2.7.0.dist-info/licenses/LICENSE
odibi-2.7.0.dist-info/METADATA
odibi-2.7.0.dist-info/WHEEL
odibi-2.7.0.dist-info/entry_points.txt
odibi-2.7.0.dist-info/top_level.txt
odibi-2.7.0.dist-info/RECORD
