Metadata-Version: 2.4
Name: odibi
Version: 2.7.0
Summary: A declarative data engineering framework - Explicit over implicit, Stories over magic
Author-email: Henry Odibi <odibiengineering@gmail.com>
License: Apache-2.0
Project-URL: Homepage, https://github.com/henryodibi11/Odibi
Project-URL: Documentation, https://github.com/henryodibi11/Odibi/tree/main/docs
Project-URL: Repository, https://github.com/henryodibi11/Odibi
Project-URL: Issues, https://github.com/henryodibi11/Odibi/issues
Keywords: data-engineering,pipeline,etl,workflow,orchestration
Classifier: Development Status :: 4 - Beta
Classifier: Intended Audience :: Developers
Classifier: License :: OSI Approved :: Apache Software License
Classifier: Programming Language :: Python :: 3
Classifier: Programming Language :: Python :: 3.9
Classifier: Programming Language :: Python :: 3.10
Classifier: Programming Language :: Python :: 3.11
Classifier: Programming Language :: Python :: 3.12
Requires-Python: >=3.9
License-File: LICENSE
Requires-Dist: pydantic<3.0.0,>=2.0.0
Requires-Dist: pyyaml<7.0,>=6.0
Requires-Dist: pandas<2.2.0,>=2.0.0
Requires-Dist: numpy<2.0.0,>=1.24.0
Requires-Dist: bottleneck<2.0.0,>=1.3.6
Requires-Dist: python-dotenv<2.0.0,>=1.0.0
Requires-Dist: markdown2<3.0.0,>=2.4.0
Requires-Dist: Jinja2<4.0.0,>=3.1.0
Requires-Dist: portalocker<3.0.0,>=2.7.0
Requires-Dist: pyarrow<17.0.0,>=14.0.0
Requires-Dist: fastapi<1.0.0,>=0.100.0
Requires-Dist: uvicorn<1.0.0,>=0.20.0
Requires-Dist: deltalake<0.30.0,>=0.18.0
Requires-Dist: rich<14.0.0,>=13.0.0
Requires-Dist: requests<3.0.0,>=2.28.0
Requires-Dist: importlib_metadata>=4.0.0
Requires-Dist: duckdb<1.1.0,>=0.9.0
Provides-Extra: cli
Requires-Dist: rich>=13.0.0; extra == "cli"
Provides-Extra: lineage
Requires-Dist: openlineage-python>=1.0.0; extra == "lineage"
Provides-Extra: telemetry
Requires-Dist: opentelemetry-api>=1.20.0; extra == "telemetry"
Requires-Dist: opentelemetry-sdk>=1.20.0; extra == "telemetry"
Requires-Dist: opentelemetry-exporter-otlp>=1.20.0; extra == "telemetry"
Provides-Extra: spark
Requires-Dist: pyspark>=3.4.0; extra == "spark"
Requires-Dist: delta-spark>=2.3.0; extra == "spark"
Provides-Extra: pandas
Requires-Dist: duckdb>=0.9.0; extra == "pandas"
Requires-Dist: pandasql>=0.7.3; extra == "pandas"
Requires-Dist: fastavro>=1.8.0; extra == "pandas"
Provides-Extra: azure
Requires-Dist: azure-storage-blob>=12.0.0; extra == "azure"
Requires-Dist: azure-identity>=1.14.0; extra == "azure"
Requires-Dist: azure-keyvault-secrets>=4.7.0; extra == "azure"
Requires-Dist: adlfs>=2023.1.0; extra == "azure"
Provides-Extra: sql
Requires-Dist: pyodbc>=5.0.0; extra == "sql"
Requires-Dist: sqlalchemy>=2.0.0; extra == "sql"
Provides-Extra: polars
Requires-Dist: polars>=0.20.0; extra == "polars"
Provides-Extra: all
Requires-Dist: pyspark>=3.4.0; extra == "all"
Requires-Dist: delta-spark>=2.3.0; extra == "all"
Requires-Dist: duckdb>=0.9.0; extra == "all"
Requires-Dist: pandasql>=0.7.3; extra == "all"
Requires-Dist: deltalake>=0.13.0; extra == "all"
Requires-Dist: fastavro>=1.8.0; extra == "all"
Requires-Dist: pyarrow>=10.0.0; extra == "all"
Requires-Dist: azure-storage-blob>=12.0.0; extra == "all"
Requires-Dist: azure-identity>=1.14.0; extra == "all"
Requires-Dist: azure-keyvault-secrets>=4.7.0; extra == "all"
Requires-Dist: adlfs>=2023.1.0; extra == "all"
Requires-Dist: pyodbc>=5.0.0; extra == "all"
Requires-Dist: sqlalchemy>=2.0.0; extra == "all"
Requires-Dist: polars>=0.20.0; extra == "all"
Requires-Dist: opentelemetry-api>=1.20.0; extra == "all"
Requires-Dist: opentelemetry-sdk>=1.20.0; extra == "all"
Requires-Dist: opentelemetry-exporter-otlp>=1.20.0; extra == "all"
Requires-Dist: openlineage-python>=1.0.0; extra == "all"
Requires-Dist: rich>=13.0.0; extra == "all"
Requires-Dist: gradio>=4.0.0; extra == "all"
Provides-Extra: dev
Requires-Dist: pytest>=7.4.0; extra == "dev"
Requires-Dist: pytest-cov>=4.1.0; extra == "dev"
Requires-Dist: black>=23.0.0; extra == "dev"
Requires-Dist: ruff>=0.1.0; extra == "dev"
Requires-Dist: mypy>=1.5.0; extra == "dev"
Requires-Dist: pre-commit>=3.4.0; extra == "dev"
Requires-Dist: pyspark>=3.4.0; extra == "dev"
Requires-Dist: delta-spark>=2.3.0; extra == "dev"
Requires-Dist: pyarrow>=10.0.0; extra == "dev"
Requires-Dist: azure-identity>=1.14.0; extra == "dev"
Requires-Dist: azure-keyvault-secrets>=4.7.0; extra == "dev"
Requires-Dist: deltalake>=0.13.0; extra == "dev"
Requires-Dist: duckdb>=0.9.0; extra == "dev"
Requires-Dist: pandasql>=0.7.3; extra == "dev"
Requires-Dist: mkdocs-material>=9.0.0; extra == "dev"
Requires-Dist: mkdocstrings[python]>=0.20.0; extra == "dev"
Requires-Dist: rich>=13.0.0; extra == "dev"
Dynamic: license-file
